cobras_ts/__init__.py
cobras_ts/cli.py
cobras_ts/cluster.py
cobras_ts/clustering.py
cobras_ts/cobras.py
cobras_ts/cobras_dtw.py
cobras_ts/cobras_kmeans.py
cobras_ts/cobras_kshape.py
cobras_ts/commandlinequerier.py
cobras_ts/labelquerier.py
cobras_ts/querier.py
cobras_ts/superinstance.py
cobras_ts/superinstance_dtw.py
cobras_ts/superinstance_kmeans.py
cobras_ts/superinstance_kshape.py
cobras_ts/visualization.py
cobras_ts/visualquerier.py
cobras_ts/cli/__init__.py
cobras_ts/cli/cli.py
cobras_ts/cli/image_to_feature_vec.py
cobras_ts/cli/webapp/__init__.py
cobras_ts/cli/webapp/main.py
cobras_ts/cli/webapp_images/__init__.py
cobras_ts/cli/webapp_images/main.py
cobras_ts/querier/__init__.py
cobras_ts/querier/commandlinequerier.py
cobras_ts/querier/labelquerier.py
cobras_ts/querier/notebookquerier_images.py
cobras_ts/querier/notebookquerier_ts.py
cobras_ts/querier/querier.py
cobras_ts/querier/visualquerier.py
cobras_ts/querier/visualquerier_images.py
cobras_ts/webapp/__init__.py
cobras_ts/webapp/main.py
cobras_ts/webapp/theme.yaml
cobras_ts/webapp/templates/index.html
cobras_ts/webapp/templates/styles.css
cobras_ts-0.1.3.dist-info/LICENSE
cobras_ts-0.1.3.dist-info/METADATA
cobras_ts-0.1.3.dist-info/WHEEL
cobras_ts-0.1.3.dist-info/entry_points.txt
cobras_ts-0.1.3.dist-info/top_level.txt
cobras_ts-0.1.3.dist-info/RECORD
