Metadata-Version: 2.1
Name: cobras-ts
Version: 0.1.3
Summary: Semi-supervised time series clustering with COBRAS
Home-page: https://dtai.cs.kuleuven.be/software/cobras/
Author: Toon Van Craenendonck
Author-email: toonvancraenendonck@gmail.com
License: UNKNOWN
Keywords: clustering timeseries semi-supervised pairwise constraints
Platform: UNKNOWN
Classifier: Development Status :: 3 - Alpha
Classifier: Intended Audience :: Developers
Classifier: Topic :: Software Development :: Build Tools
Classifier: License :: OSI Approved :: MIT License
Classifier: Programming Language :: Python :: 3
Requires-Python: >=3.5
Requires-Dist: dtaidistance
Requires-Dist: kshape
Requires-Dist: numpy
Requires-Dist: scikit-learn[alldeps]
Provides-Extra: dev
Requires-Dist: check-manifest ; extra == 'dev'
Requires-Dist: sphinx-rtd-theme ; extra == 'dev'
Provides-Extra: gui
Requires-Dist: bokeh (>=0.12.15) ; extra == 'gui'
Requires-Dist: cloudpickle ; extra == 'gui'
Requires-Dist: datashader ; extra == 'gui'
Requires-Dist: pygments ; extra == 'gui'
Provides-Extra: images
Requires-Dist: tensorflow ; extra == 'images'
Provides-Extra: test
Requires-Dist: coverage ; extra == 'test'
